hyshlr/.gitignore
hyshlr/__init__.py
donjon_hyshlr-1.0.1.dist-info/METADATA
donjon_hyshlr-1.0.1.dist-info/WHEEL
donjon_hyshlr-1.0.1.dist-info/RECORD
